gpt4free/__init__.py
gpt4free/forefront/__init__.py
gpt4free/forefront/typing.py
gpt4free/italygpt/__init__.py
gpt4free/theb/__init__.py
gpt4free/theb/theb_test.py
gpt4free/usesless/__init__.py
gpt4free/you/__init__.py
gpt4free-1.0.2.dist-info/AUTHORS.md
gpt4free-1.0.2.dist-info/LICENSE
gpt4free-1.0.2.dist-info/METADATA
gpt4free-1.0.2.dist-info/WHEEL
gpt4free-1.0.2.dist-info/top_level.txt
gpt4free-1.0.2.dist-info/RECORD
