Metadata-Version: 2.1
Name: gpt4free
Version: 1.0.2
Summary: decentralising the Ai Industry, just some language model api's...
Home-page: https://github.com/rzashakeri/gpt4free-python-package
Author: Reza Shakeri
Author-email: rzashakeri@gmail.com
License: GNU General Public License v3
Project-URL: Homepage, https://github.com/rzashakeri/gpt4free-python-package
Project-URL: Issue tracker, https://github.com/rzashakeri/gpt4free-python-package/issues
Project-URL: Release notes, https://github.com/rzashakeri/gpt4free-python-package/releases
Project-URL: Source, https://github.com/rzashakeri/gpt4free-python-package
Project-URL: Discussions, https://github.com/rzashakeri/gpt4free-python-package/discussions
Keywords: gpt4free,ChatGPT,Free,FreeChatGPT,Ai
Classifier: Development Status :: 5 - Production/Stable
Classifier: Intended Audience :: Developers
Classifier: License :: OSI Approved :: GNU General Public License v3 (GPLv3)
Classifier: Natural Language :: English
Classifier: Programming Language :: Python :: 3
Classifier: Programming Language :: Python :: 3.8
Classifier: Programming Language :: Python :: 3.9
Classifier: Programming Language :: Python :: 3.10
Requires-Python: >=3.6
License-File: LICENSE
License-File: AUTHORS.md
Requires-Dist: websocket-client
Requires-Dist: requests
Requires-Dist: tls-client
Requires-Dist: pypasser
Requires-Dist: names
Requires-Dist: colorama
Requires-Dist: curl-cffi
Requires-Dist: streamlit (==1.21.0)
Requires-Dist: selenium
Requires-Dist: fake-useragent
Requires-Dist: twocaptcha
Requires-Dist: pydantic
Requires-Dist: pymailtm
Requires-Dist: beautifulsoup4
